{
  "ID": "698adf30-b5e5-4d2d-8e28-2053c556682a",
  "Root": {
    "alive": true,
    "content": [
      "fddef238-2814-4638-87a3-38d84195f90b",
      "4eafecfb-ac91-4aeb-89ed-96bf62b58272",
      "6945ca7c-2602-4aed-b52f-caea645c54f8",
      "dc40674e-0547-4012-9138-f22cfaa09d63",
      "1011d0f1-2e00-43a8-9d72-4e1438a2505a",
      "30ba593a-b1d1-4ac1-958f-bcc51e705371",
      "ff29d8e6-da42-4aad-899b-7339cde54122",
      "10d68653-d22b-450e-a3bd-9e8c379064a8",
      "63df712f-4ac1-4703-b35f-69094b084f1c",
      "a09caee7-930a-4676-b6ae-2d5264ac9167"
    ],
    "created_by": "bb760e2d-d679-4b64-b2a9-03005b21870a",
    "created_time": 1532156234149,
    "format": {
      "page_full_width": true,
      "page_small_text": true
    },
    "id": "698adf30-b5e5-4d2d-8e28-2053c556682a",
    "ignore_block_count": true,
    "last_edited_by": "bb760e2d-d679-4b64-b2a9-03005b21870a",
    "last_edited_time": 1539852453618,
    "parent_id": "7ccfe169-7c31-49c3-83b6-8894ede37d84",
    "parent_table": "block",
    "properties": {
      "title": [
        [
          "Interface \u0026 polymorphism"
        ]
      ]
    },
    "type": "page",
    "version": 92,
    "content_resolved": [
      {
        "alive": true,
        "created_by": "bb760e2d-d679-4b64-b2a9-03005b21870a",
        "created_time": 1532213702627,
        "id": "fddef238-2814-4638-87a3-38d84195f90b",
        "last_edited_by": "bb760e2d-d679-4b64-b2a9-03005b21870a",
        "last_edited_time": 1532213707770,
        "parent_id": "698adf30-b5e5-4d2d-8e28-2053c556682a",
        "parent_table": "block",
        "properties": {
          "title": [
            [
              "$Id: 284"
            ]
          ]
        },
        "type": "text",
        "version": 10,
        "inline_content": [
          {
            "Text": "$Id: 284"
          }
        ]
      },
      {
        "alive": true,
        "created_by": "bb760e2d-d679-4b64-b2a9-03005b21870a",
        "created_time": 1532213707770,
        "id": "4eafecfb-ac91-4aeb-89ed-96bf62b58272",
        "last_edited_by": "bb760e2d-d679-4b64-b2a9-03005b21870a",
        "last_edited_time": 1532213710273,
        "parent_id": "698adf30-b5e5-4d2d-8e28-2053c556682a",
        "parent_table": "block",
        "properties": {
          "title": [
            [
              "$Score: 1"
            ]
          ]
        },
        "type": "text",
        "version": 14,
        "inline_content": [
          {
            "Text": "$Score: 1"
          }
        ]
      },
      {
        "alive": true,
        "created_by": "bb760e2d-d679-4b64-b2a9-03005b21870a",
        "created_time": 1532213710273,
        "id": "6945ca7c-2602-4aed-b52f-caea645c54f8",
        "last_edited_by": "bb760e2d-d679-4b64-b2a9-03005b21870a",
        "last_edited_time": 1532213712353,
        "parent_id": "698adf30-b5e5-4d2d-8e28-2053c556682a",
        "parent_table": "block",
        "properties": {
          "title": [
            [
              "$SOId: 27429"
            ]
          ]
        },
        "type": "text",
        "version": 10,
        "inline_content": [
          {
            "Text": "$SOId: 27429"
          }
        ]
      },
      {
        "alive": true,
        "created_by": "bb760e2d-d679-4b64-b2a9-03005b21870a",
        "created_time": 1539454320166,
        "id": "dc40674e-0547-4012-9138-f22cfaa09d63",
        "last_edited_by": "bb760e2d-d679-4b64-b2a9-03005b21870a",
        "last_edited_time": 1539454320166,
        "parent_id": "698adf30-b5e5-4d2d-8e28-2053c556682a",
        "parent_table": "block",
        "type": "text",
        "version": 4
      },
      {
        "alive": true,
        "created_by": "bb760e2d-d679-4b64-b2a9-03005b21870a",
        "created_time": 1532213714425,
        "id": "1011d0f1-2e00-43a8-9d72-4e1438a2505a",
        "last_edited_by": "bb760e2d-d679-4b64-b2a9-03005b21870a",
        "last_edited_time": 1539454444323,
        "parent_id": "698adf30-b5e5-4d2d-8e28-2053c556682a",
        "parent_table": "block",
        "properties": {
          "title": [
            [
              "Interface defines a set of methods on a struct. It defines behavior."
            ]
          ]
        },
        "type": "text",
        "version": 274,
        "inline_content": [
          {
            "Text": "Interface defines a set of methods on a struct. It defines behavior."
          }
        ]
      },
      {
        "alive": true,
        "created_by": "bb760e2d-d679-4b64-b2a9-03005b21870a",
        "created_time": 1539454444872,
        "id": "30ba593a-b1d1-4ac1-958f-bcc51e705371",
        "last_edited_by": "bb760e2d-d679-4b64-b2a9-03005b21870a",
        "last_edited_time": 1539454480249,
        "parent_id": "698adf30-b5e5-4d2d-8e28-2053c556682a",
        "parent_table": "block",
        "properties": {
          "title": [
            [
              "Interface cannot define data."
            ]
          ]
        },
        "type": "text",
        "version": 112,
        "inline_content": [
          {
            "Text": "Interface cannot define data."
          }
        ]
      },
      {
        "alive": true,
        "created_by": "bb760e2d-d679-4b64-b2a9-03005b21870a",
        "created_time": 1539454506090,
        "id": "ff29d8e6-da42-4aad-899b-7339cde54122",
        "last_edited_by": "bb760e2d-d679-4b64-b2a9-03005b21870a",
        "last_edited_time": 1539454552866,
        "parent_id": "698adf30-b5e5-4d2d-8e28-2053c556682a",
        "parent_table": "block",
        "properties": {
          "title": [
            [
              "It allows functions to accept multiple implementation of the same functionality."
            ]
          ]
        },
        "type": "text",
        "version": 174,
        "inline_content": [
          {
            "Text": "It allows functions to accept multiple implementation of the same functionality."
          }
        ]
      },
      {
        "alive": true,
        "created_by": "bb760e2d-d679-4b64-b2a9-03005b21870a",
        "created_time": 1539454553598,
        "id": "10d68653-d22b-450e-a3bd-9e8c379064a8",
        "last_edited_by": "bb760e2d-d679-4b64-b2a9-03005b21870a",
        "last_edited_time": 1539454597786,
        "parent_id": "698adf30-b5e5-4d2d-8e28-2053c556682a",
        "parent_table": "block",
        "properties": {
          "title": [
            [
              "This is similar (but not identical) to the notion of virtual methods in C++."
            ]
          ]
        },
        "type": "text",
        "version": 200,
        "inline_content": [
          {
            "Text": "This is similar (but not identical) to the notion of virtual methods in C++."
          }
        ]
      },
      {
        "alive": true,
        "created_by": "bb760e2d-d679-4b64-b2a9-03005b21870a",
        "created_time": 1539852426966,
        "format": {
          "block_width": 800,
          "block_height": 600,
          "display_source": "https://repl.it/@kjk1/gobook-oo-interface-polymorhism?lite=true",
          "block_full_width": false,
          "block_page_width": false,
          "block_preserve_scale": false
        },
        "id": "63df712f-4ac1-4703-b35f-69094b084f1c",
        "last_edited_by": "bb760e2d-d679-4b64-b2a9-03005b21870a",
        "last_edited_time": 1539852428534,
        "parent_id": "698adf30-b5e5-4d2d-8e28-2053c556682a",
        "parent_table": "block",
        "properties": {
          "source": [
            [
              "https://repl.it/@kjk1/gobook-oo-interface-polymorhism"
            ]
          ]
        },
        "type": "embed",
        "version": 8,
        "source": "https://repl.it/@kjk1/gobook-oo-interface-polymorhism",
        "format_embed": {
          "block_full_width": false,
          "block_height": 600,
          "block_page_width": false,
          "block_preserve_scale": false,
          "display_source": "https://repl.it/@kjk1/gobook-oo-interface-polymorhism?lite=true"
        }
      },
      {
        "alive": true,
        "created_by": "bb760e2d-d679-4b64-b2a9-03005b21870a",
        "created_time": 1539454679676,
        "id": "a09caee7-930a-4676-b6ae-2d5264ac9167",
        "last_edited_by": "bb760e2d-d679-4b64-b2a9-03005b21870a",
        "last_edited_time": 1539454679702,
        "parent_id": "698adf30-b5e5-4d2d-8e28-2053c556682a",
        "parent_table": "block",
        "type": "text",
        "version": 6
      }
    ],
    "title": "Interface \u0026 polymorphism",
    "format_page": {
      "page_cover": "",
      "page_cover_position": 0,
      "page_font": "",
      "page_full_width": true,
      "page_icon": "",
      "page_small_text": true
    }
  },
  "Users": [
    {
      "email": "kkowalczyk@gmail.com",
      "family_name": "Kowalczyk",
      "given_name": "Krzysztof",
      "id": "bb760e2d-d679-4b64-b2a9-03005b21870a",
      "locale": "en",
      "mobile_onboarding_completed": true,
      "onboarding_completed": true,
      "profile_photo": "https://s3-us-west-2.amazonaws.com/public.notion-static.com/2dcaa66c-7674-4ff6-9924-601785b63561/head-bw-640x960.png",
      "time_zone": "America/Los_Angeles",
      "version": 10
    }
  ],
  "Tables": null
}