{
  "ID": "2ade0562-a918-41e1-844d-4044b79f936c",
  "Root": {
    "alive": true,
    "content": [
      "1806dec4-1811-4bdc-b207-1c1a71c2e632",
      "b8932b23-3419-4c4a-a238-b2fa6a17f079",
      "278d0331-6ae4-4bef-877c-df44ca46a44a",
      "acea174f-93eb-4b3c-84f3-b9afc31758c9",
      "e101fde0-84fc-47ba-a382-7f7b414b6935"
    ],
    "created_by": "bb760e2d-d679-4b64-b2a9-03005b21870a",
    "created_time": 1532155967169,
    "format": {
      "page_full_width": true,
      "page_small_text": true
    },
    "id": "2ade0562-a918-41e1-844d-4044b79f936c",
    "ignore_block_count": true,
    "last_edited_by": "bb760e2d-d679-4b64-b2a9-03005b21870a",
    "last_edited_time": 1532234408909,
    "parent_id": "ccc8d069-58ae-4431-9b21-f9973716e3ca",
    "parent_table": "block",
    "properties": {
      "title": [
        [
          "Replace strings"
        ]
      ]
    },
    "type": "page",
    "version": 23,
    "content_resolved": [
      {
        "alive": true,
        "created_by": "bb760e2d-d679-4b64-b2a9-03005b21870a",
        "created_time": 1532195697236,
        "id": "1806dec4-1811-4bdc-b207-1c1a71c2e632",
        "last_edited_by": "bb760e2d-d679-4b64-b2a9-03005b21870a",
        "last_edited_time": 1532234409903,
        "parent_id": "2ade0562-a918-41e1-844d-4044b79f936c",
        "parent_table": "block",
        "properties": {
          "title": [
            [
              "$Search: Replace substring"
            ]
          ]
        },
        "type": "text",
        "version": 12,
        "inline_content": [
          {
            "Text": "$Search: Replace substring"
          }
        ]
      },
      {
        "alive": true,
        "created_by": "bb760e2d-d679-4b64-b2a9-03005b21870a",
        "created_time": 1532195699454,
        "id": "b8932b23-3419-4c4a-a238-b2fa6a17f079",
        "last_edited_by": "bb760e2d-d679-4b64-b2a9-03005b21870a",
        "last_edited_time": 1532234410612,
        "parent_id": "2ade0562-a918-41e1-844d-4044b79f936c",
        "parent_table": "block",
        "properties": {
          "title": [
            [
              "$Id: 48"
            ]
          ]
        },
        "type": "text",
        "version": 12,
        "inline_content": [
          {
            "Text": "$Id: 48"
          }
        ]
      },
      {
        "alive": true,
        "created_by": "bb760e2d-d679-4b64-b2a9-03005b21870a",
        "created_time": 1532195702549,
        "id": "278d0331-6ae4-4bef-877c-df44ca46a44a",
        "last_edited_by": "bb760e2d-d679-4b64-b2a9-03005b21870a",
        "last_edited_time": 1532234411298,
        "parent_id": "2ade0562-a918-41e1-844d-4044b79f936c",
        "parent_table": "block",
        "properties": {
          "title": [
            [
              "$SOId: 5eq100h1"
            ]
          ]
        },
        "type": "text",
        "version": 14,
        "inline_content": [
          {
            "Text": "$SOId: 5eq100h1"
          }
        ]
      },
      {
        "alive": true,
        "created_by": "bb760e2d-d679-4b64-b2a9-03005b21870a",
        "created_time": 1532195704959,
        "id": "acea174f-93eb-4b3c-84f3-b9afc31758c9",
        "last_edited_by": "bb760e2d-d679-4b64-b2a9-03005b21870a",
        "last_edited_time": 1532195704959,
        "parent_id": "2ade0562-a918-41e1-844d-4044b79f936c",
        "parent_table": "block",
        "type": "text",
        "version": 6
      },
      {
        "alive": true,
        "created_by": "bb760e2d-d679-4b64-b2a9-03005b21870a",
        "created_time": 1532155967169,
        "id": "e101fde0-84fc-47ba-a382-7f7b414b6935",
        "ignore_block_count": true,
        "last_edited_by": "bb760e2d-d679-4b64-b2a9-03005b21870a",
        "last_edited_time": 1532155967169,
        "parent_id": "2ade0562-a918-41e1-844d-4044b79f936c",
        "parent_table": "block",
        "properties": {
          "title": [
            [
              "@file replace.go output sha1:99e389587a0e7676e2fe56b35b70e7fe8d6ee4dd goplayground:03B_lmMfFh5"
            ]
          ]
        },
        "type": "text",
        "version": 1,
        "inline_content": [
          {
            "Text": "@file replace.go output sha1:99e389587a0e7676e2fe56b35b70e7fe8d6ee4dd goplayground:03B_lmMfFh5"
          }
        ]
      }
    ],
    "title": "Replace strings",
    "format_page": {
      "page_cover": "",
      "page_cover_position": 0,
      "page_font": "",
      "page_full_width": true,
      "page_icon": "",
      "page_small_text": true
    }
  },
  "Users": [
    {
      "email": "kkowalczyk@gmail.com",
      "family_name": "Kowalczyk",
      "given_name": "Krzysztof",
      "id": "bb760e2d-d679-4b64-b2a9-03005b21870a",
      "locale": "en",
      "mobile_onboarding_completed": true,
      "onboarding_completed": true,
      "profile_photo": "https://s3-us-west-2.amazonaws.com/public.notion-static.com/2dcaa66c-7674-4ff6-9924-601785b63561/head-bw-640x960.png",
      "time_zone": "America/Los_Angeles",
      "version": 10
    }
  ],
  "Tables": null
}