{
  "ID": "77498e7b-3d31-464c-9def-3316dfe26415",
  "Root": {
    "alive": true,
    "content": [
      "331e4aec-943a-48cb-b35f-1cd2a43ebcf5",
      "5ce6bbfb-7b08-463f-b857-55a3af11c585",
      "9537bb77-00d4-4009-900b-5a39422f88a7",
      "6bd7d47d-f3a7-47c2-a340-218370eb3190",
      "31d468c4-fdd3-474c-91b0-09ca406b5fce",
      "9de0c10d-a620-4dca-86b9-e24b17f120c9",
      "b0dc4cd3-c668-4c1d-b62a-1c45ccaa3a39",
      "767e5dc0-6d60-4c32-a6a8-a32f84789f6b",
      "4a58b50c-93f8-4f70-bb37-f39c7de8a250",
      "66055cab-6e69-445d-9e41-9e26c258a19c",
      "b9f80cb1-1251-454c-a903-d3ef348aebf1",
      "a029c9c8-c13f-44b7-b965-62297fffe510",
      "1a9b3f8f-815b-4626-be27-3944aee5b8c7",
      "83ae8777-c47e-40bb-aea3-9cde629df335",
      "6874c54e-9d5f-4e4d-b38f-f9efbcc2c8b8",
      "4a840141-6e9c-4e63-9b3d-5e6acd9bd80d",
      "aff96c5b-9b4f-40e6-920f-6e0f53ae0f46",
      "91c97f61-5548-479b-86a8-d25ec2624051",
      "e9b38632-de10-404f-9dfa-f385a99a0b19"
    ],
    "created_by": "bb760e2d-d679-4b64-b2a9-03005b21870a",
    "created_time": 1532156023177,
    "format": {
      "page_full_width": true,
      "page_small_text": true
    },
    "id": "77498e7b-3d31-464c-9def-3316dfe26415",
    "ignore_block_count": true,
    "last_edited_by": "bb760e2d-d679-4b64-b2a9-03005b21870a",
    "last_edited_time": 1538892255956,
    "parent_id": "fd755f13-f0fc-4e75-ad9b-9ee675e557e8",
    "parent_table": "block",
    "properties": {
      "title": [
        [
          "switch statement"
        ]
      ]
    },
    "type": "page",
    "version": 90,
    "content_resolved": [
      {
        "alive": true,
        "created_by": "bb760e2d-d679-4b64-b2a9-03005b21870a",
        "created_time": 1532203253184,
        "id": "331e4aec-943a-48cb-b35f-1cd2a43ebcf5",
        "last_edited_by": "bb760e2d-d679-4b64-b2a9-03005b21870a",
        "last_edited_time": 1532235736999,
        "parent_id": "77498e7b-3d31-464c-9def-3316dfe26415",
        "parent_table": "block",
        "properties": {
          "title": [
            [
              "$Id: 99"
            ]
          ]
        },
        "type": "text",
        "version": 14,
        "inline_content": [
          {
            "Text": "$Id: 99"
          }
        ]
      },
      {
        "alive": true,
        "created_by": "bb760e2d-d679-4b64-b2a9-03005b21870a",
        "created_time": 1532203257938,
        "id": "5ce6bbfb-7b08-463f-b857-55a3af11c585",
        "last_edited_by": "bb760e2d-d679-4b64-b2a9-03005b21870a",
        "last_edited_time": 1532235737776,
        "parent_id": "77498e7b-3d31-464c-9def-3316dfe26415",
        "parent_table": "block",
        "properties": {
          "title": [
            [
              "$SOId: 4377"
            ]
          ]
        },
        "type": "text",
        "version": 12,
        "inline_content": [
          {
            "Text": "$SOId: 4377"
          }
        ]
      },
      {
        "alive": true,
        "created_by": "bb760e2d-d679-4b64-b2a9-03005b21870a",
        "created_time": 1532203262994,
        "id": "9537bb77-00d4-4009-900b-5a39422f88a7",
        "last_edited_by": "bb760e2d-d679-4b64-b2a9-03005b21870a",
        "last_edited_time": 1532203262994,
        "parent_id": "77498e7b-3d31-464c-9def-3316dfe26415",
        "parent_table": "block",
        "type": "text",
        "version": 4
      },
      {
        "alive": true,
        "created_by": "bb760e2d-d679-4b64-b2a9-03005b21870a",
        "created_time": 1532203259706,
        "id": "6bd7d47d-f3a7-47c2-a340-218370eb3190",
        "last_edited_by": "bb760e2d-d679-4b64-b2a9-03005b21870a",
        "last_edited_time": 1532203261035,
        "parent_id": "77498e7b-3d31-464c-9def-3316dfe26415",
        "parent_table": "block",
        "properties": {
          "title": [
            [
              "A simple "
            ],
            [
              "switch",
              [
                [
                  "c"
                ]
              ]
            ],
            [
              " statement:"
            ]
          ]
        },
        "type": "text",
        "version": 12,
        "inline_content": [
          {
            "Text": "A simple "
          },
          {
            "Text": "switch",
            "AttrFlags": 2
          },
          {
            "Text": " statement:"
          }
        ]
      },
      {
        "alive": true,
        "created_by": "bb760e2d-d679-4b64-b2a9-03005b21870a",
        "created_time": 1538891806816,
        "format": {
          "block_height": 368.0000305175781,
          "display_source": "https://www.onlinetool.io/gitoembed/widget?url=https%3A%2F%2Fgithub.com%2Fessentialbooks%2Fbooks%2Fblob%2Fmaster%2Fbooks%2Fgo%2F0130-if-switch-goto%2Fcase.go",
          "block_full_width": false,
          "block_page_width": true,
          "block_preserve_scale": false
        },
        "id": "31d468c4-fdd3-474c-91b0-09ca406b5fce",
        "last_edited_by": "bb760e2d-d679-4b64-b2a9-03005b21870a",
        "last_edited_time": 1538892016673,
        "parent_id": "77498e7b-3d31-464c-9def-3316dfe26415",
        "parent_table": "block",
        "properties": {
          "source": [
            [
              "https://www.onlinetool.io/gitoembed/widget?url=https%3A%2F%2Fgithub.com%2Fessentialbooks%2Fbooks%2Fblob%2Fmaster%2Fbooks%2Fgo%2F0130-if-switch-goto%2Fcase.go"
            ]
          ]
        },
        "type": "embed",
        "version": 12,
        "format_embed": {
          "block_full_width": false,
          "block_height": 368.0000305175781,
          "block_page_width": true,
          "block_preserve_scale": false,
          "display_source": "https://www.onlinetool.io/gitoembed/widget?url=https%3A%2F%2Fgithub.com%2Fessentialbooks%2Fbooks%2Fblob%2Fmaster%2Fbooks%2Fgo%2F0130-if-switch-goto%2Fcase.go"
        }
      },
      {
        "alive": true,
        "created_by": "bb760e2d-d679-4b64-b2a9-03005b21870a",
        "created_time": 1538890570721,
        "id": "9de0c10d-a620-4dca-86b9-e24b17f120c9",
        "last_edited_by": "bb760e2d-d679-4b64-b2a9-03005b21870a",
        "last_edited_time": 1538890888171,
        "parent_id": "77498e7b-3d31-464c-9def-3316dfe26415",
        "parent_table": "block",
        "properties": {
          "title": [
            [
              "fallthrough"
            ]
          ]
        },
        "type": "header",
        "version": 60,
        "inline_content": [
          {
            "Text": "fallthrough"
          }
        ]
      },
      {
        "alive": true,
        "created_by": "bb760e2d-d679-4b64-b2a9-03005b21870a",
        "created_time": 1538890889153,
        "id": "b0dc4cd3-c668-4c1d-b62a-1c45ccaa3a39",
        "last_edited_by": "bb760e2d-d679-4b64-b2a9-03005b21870a",
        "last_edited_time": 1538891180886,
        "parent_id": "77498e7b-3d31-464c-9def-3316dfe26415",
        "parent_table": "block",
        "properties": {
          "title": [
            [
              "Unlike most other languages like C++ or Java, you don't have to use "
            ],
            [
              "break",
              [
                [
                  "c"
                ]
              ]
            ],
            [
              " to stop one "
            ],
            [
              "case",
              [
                [
                  "c"
                ]
              ]
            ],
            [
              " into continuing execution in following "
            ],
            [
              "case",
              [
                [
                  "c"
                ]
              ]
            ],
            [
              "."
            ]
          ]
        },
        "type": "text",
        "version": 408,
        "inline_content": [
          {
            "Text": "Unlike most other languages like C++ or Java, you don't have to use "
          },
          {
            "Text": "break",
            "AttrFlags": 2
          },
          {
            "Text": " to stop one "
          },
          {
            "Text": "case",
            "AttrFlags": 2
          },
          {
            "Text": " into continuing execution in following "
          },
          {
            "Text": "case",
            "AttrFlags": 2
          },
          {
            "Text": "."
          }
        ]
      },
      {
        "alive": true,
        "created_by": "bb760e2d-d679-4b64-b2a9-03005b21870a",
        "created_time": 1538891181854,
        "id": "767e5dc0-6d60-4c32-a6a8-a32f84789f6b",
        "last_edited_by": "bb760e2d-d679-4b64-b2a9-03005b21870a",
        "last_edited_time": 1538891200396,
        "parent_id": "77498e7b-3d31-464c-9def-3316dfe26415",
        "parent_table": "block",
        "properties": {
          "title": [
            [
              "Such default behavior is a frequent source of bugs."
            ]
          ]
        },
        "type": "text",
        "version": 144,
        "inline_content": [
          {
            "Text": "Such default behavior is a frequent source of bugs."
          }
        ]
      },
      {
        "alive": true,
        "created_by": "bb760e2d-d679-4b64-b2a9-03005b21870a",
        "created_time": 1538891200685,
        "id": "4a58b50c-93f8-4f70-bb37-f39c7de8a250",
        "last_edited_by": "bb760e2d-d679-4b64-b2a9-03005b21870a",
        "last_edited_time": 1538892076798,
        "parent_id": "77498e7b-3d31-464c-9def-3316dfe26415",
        "parent_table": "block",
        "properties": {
          "title": [
            [
              "Instead in Go you can ask for such behavior with "
            ],
            [
              "fallthrough",
              [
                [
                  "c"
                ]
              ]
            ],
            [
              ":"
            ]
          ]
        },
        "type": "text",
        "version": 172,
        "inline_content": [
          {
            "Text": "Instead in Go you can ask for such behavior with "
          },
          {
            "Text": "fallthrough",
            "AttrFlags": 2
          },
          {
            "Text": ":"
          }
        ]
      },
      {
        "alive": true,
        "created_by": "bb760e2d-d679-4b64-b2a9-03005b21870a",
        "created_time": 1538891837534,
        "format": {
          "block_height": 356.9965515136719,
          "display_source": "https://www.onlinetool.io/gitoembed/widget?url=https%3A%2F%2Fgithub.com%2Fessentialbooks%2Fbooks%2Fblob%2Fmaster%2Fbooks%2Fgo%2F0130-if-switch-goto%2Ffallthrough.go",
          "block_full_width": false,
          "block_page_width": true,
          "block_preserve_scale": false
        },
        "id": "66055cab-6e69-445d-9e41-9e26c258a19c",
        "last_edited_by": "bb760e2d-d679-4b64-b2a9-03005b21870a",
        "last_edited_time": 1538892020329,
        "parent_id": "77498e7b-3d31-464c-9def-3316dfe26415",
        "parent_table": "block",
        "properties": {
          "source": [
            [
              "https://www.onlinetool.io/gitoembed/widget?url=https%3A%2F%2Fgithub.com%2Fessentialbooks%2Fbooks%2Fblob%2Fmaster%2Fbooks%2Fgo%2F0130-if-switch-goto%2Ffallthrough.go"
            ]
          ]
        },
        "type": "embed",
        "version": 12,
        "format_embed": {
          "block_full_width": false,
          "block_height": 356.9965515136719,
          "block_page_width": true,
          "block_preserve_scale": false,
          "display_source": "https://www.onlinetool.io/gitoembed/widget?url=https%3A%2F%2Fgithub.com%2Fessentialbooks%2Fbooks%2Fblob%2Fmaster%2Fbooks%2Fgo%2F0130-if-switch-goto%2Ffallthrough.go"
        }
      },
      {
        "alive": true,
        "created_by": "bb760e2d-d679-4b64-b2a9-03005b21870a",
        "created_time": 1538892050792,
        "id": "b9f80cb1-1251-454c-a903-d3ef348aebf1",
        "last_edited_by": "bb760e2d-d679-4b64-b2a9-03005b21870a",
        "last_edited_time": 1538892075363,
        "parent_id": "77498e7b-3d31-464c-9def-3316dfe26415",
        "parent_table": "block",
        "properties": {
          "title": [
            [
              "Switch on strings"
            ]
          ]
        },
        "type": "header",
        "version": 75,
        "inline_content": [
          {
            "Text": "Switch on strings"
          }
        ]
      },
      {
        "alive": true,
        "created_by": "bb760e2d-d679-4b64-b2a9-03005b21870a",
        "created_time": 1538892094346,
        "id": "a029c9c8-c13f-44b7-b965-62297fffe510",
        "last_edited_by": "bb760e2d-d679-4b64-b2a9-03005b21870a",
        "last_edited_time": 1538892140406,
        "parent_id": "77498e7b-3d31-464c-9def-3316dfe26415",
        "parent_table": "block",
        "properties": {
          "title": [
            [
              "Switch in Go is more flexible than in languages like C++ or Java. For example, we can "
            ],
            [
              "switch",
              [
                [
                  "c"
                ]
              ]
            ],
            [
              " on strings:"
            ]
          ]
        },
        "type": "text",
        "version": 338,
        "inline_content": [
          {
            "Text": "Switch in Go is more flexible than in languages like C++ or Java. For example, we can "
          },
          {
            "Text": "switch",
            "AttrFlags": 2
          },
          {
            "Text": " on strings:"
          }
        ]
      },
      {
        "alive": true,
        "created_by": "bb760e2d-d679-4b64-b2a9-03005b21870a",
        "created_time": 1538892255956,
        "format": {
          "block_height": 335.0000305175781,
          "display_source": "https://www.onlinetool.io/gitoembed/widget?url=https%3A%2F%2Fgithub.com%2Fessentialbooks%2Fbooks%2Fblob%2Fmaster%2Fbooks%2Fgo%2F0130-if-switch-goto%2Fswitch_string.go",
          "block_full_width": false,
          "block_page_width": true,
          "block_preserve_scale": false
        },
        "id": "1a9b3f8f-815b-4626-be27-3944aee5b8c7",
        "last_edited_by": "bb760e2d-d679-4b64-b2a9-03005b21870a",
        "last_edited_time": 1538892265042,
        "parent_id": "77498e7b-3d31-464c-9def-3316dfe26415",
        "parent_table": "block",
        "properties": {
          "source": [
            [
              "https://www.onlinetool.io/gitoembed/widget?url=https%3A%2F%2Fgithub.com%2Fessentialbooks%2Fbooks%2Fblob%2Fmaster%2Fbooks%2Fgo%2F0130-if-switch-goto%2Fswitch_string.go"
            ]
          ]
        },
        "type": "embed",
        "version": 12,
        "format_embed": {
          "block_full_width": false,
          "block_height": 335.0000305175781,
          "block_page_width": true,
          "block_preserve_scale": false,
          "display_source": "https://www.onlinetool.io/gitoembed/widget?url=https%3A%2F%2Fgithub.com%2Fessentialbooks%2Fbooks%2Fblob%2Fmaster%2Fbooks%2Fgo%2F0130-if-switch-goto%2Fswitch_string.go"
        }
      },
      {
        "alive": true,
        "created_by": "bb760e2d-d679-4b64-b2a9-03005b21870a",
        "created_time": 1532156023176,
        "id": "83ae8777-c47e-40bb-aea3-9cde629df335",
        "ignore_block_count": true,
        "last_edited_by": "bb760e2d-d679-4b64-b2a9-03005b21870a",
        "last_edited_time": 1532156023176,
        "parent_id": "77498e7b-3d31-464c-9def-3316dfe26415",
        "parent_table": "block",
        "properties": {
          "title": [
            [
              "An empty switch expression is implicitly "
            ],
            [
              "true",
              [
                [
                  "c"
                ]
              ]
            ],
            [
              ":"
            ]
          ]
        },
        "type": "text",
        "version": 1,
        "inline_content": [
          {
            "Text": "An empty switch expression is implicitly "
          },
          {
            "Text": "true",
            "AttrFlags": 2
          },
          {
            "Text": ":"
          }
        ]
      },
      {
        "alive": true,
        "created_by": "bb760e2d-d679-4b64-b2a9-03005b21870a",
        "created_time": 1532156023176,
        "id": "6874c54e-9d5f-4e4d-b38f-f9efbcc2c8b8",
        "ignore_block_count": true,
        "last_edited_by": "bb760e2d-d679-4b64-b2a9-03005b21870a",
        "last_edited_time": 1532203242294,
        "parent_id": "77498e7b-3d31-464c-9def-3316dfe26415",
        "parent_table": "block",
        "properties": {
          "language": [
            [
              "Go"
            ]
          ],
          "title": [
            [
              "switch {\ncase a + b == c:\n    // do something\ncase a + b == d:\n    // do something else\n}"
            ]
          ]
        },
        "type": "code",
        "version": 3,
        "code": "switch {\ncase a + b == c:\n    // do something\ncase a + b == d:\n    // do something else\n}",
        "code_language": "Go"
      },
      {
        "alive": true,
        "created_by": "bb760e2d-d679-4b64-b2a9-03005b21870a",
        "created_time": 1532156023176,
        "id": "4a840141-6e9c-4e63-9b3d-5e6acd9bd80d",
        "ignore_block_count": true,
        "last_edited_by": "bb760e2d-d679-4b64-b2a9-03005b21870a",
        "last_edited_time": 1538891977734,
        "parent_id": "77498e7b-3d31-464c-9def-3316dfe26415",
        "parent_table": "block",
        "properties": {
          "title": [
            [
              "Switch statements support a simple statement similar to "
            ],
            [
              "if",
              [
                [
                  "c"
                ]
              ]
            ],
            [
              " statements:"
            ]
          ]
        },
        "type": "text",
        "version": 5,
        "inline_content": [
          {
            "Text": "Switch statements support a simple statement similar to "
          },
          {
            "Text": "if",
            "AttrFlags": 2
          },
          {
            "Text": " statements:"
          }
        ]
      },
      {
        "alive": true,
        "created_by": "bb760e2d-d679-4b64-b2a9-03005b21870a",
        "created_time": 1532156023177,
        "id": "aff96c5b-9b4f-40e6-920f-6e0f53ae0f46",
        "ignore_block_count": true,
        "last_edited_by": "bb760e2d-d679-4b64-b2a9-03005b21870a",
        "last_edited_time": 1532203246031,
        "parent_id": "77498e7b-3d31-464c-9def-3316dfe26415",
        "parent_table": "block",
        "properties": {
          "language": [
            [
              "Go"
            ]
          ],
          "title": [
            [
              "switch n := getNumber(); n {\ncase 1:\n    // do something\ncase 2:\n    // do something else\n}"
            ]
          ]
        },
        "type": "code",
        "version": 3,
        "code": "switch n := getNumber(); n {\ncase 1:\n    // do something\ncase 2:\n    // do something else\n}",
        "code_language": "Go"
      },
      {
        "alive": true,
        "created_by": "bb760e2d-d679-4b64-b2a9-03005b21870a",
        "created_time": 1532156023177,
        "id": "91c97f61-5548-479b-86a8-d25ec2624051",
        "ignore_block_count": true,
        "last_edited_by": "bb760e2d-d679-4b64-b2a9-03005b21870a",
        "last_edited_time": 1532156023177,
        "parent_id": "77498e7b-3d31-464c-9def-3316dfe26415",
        "parent_table": "block",
        "properties": {
          "title": [
            [
              "Cases can be combined in a comma-separated list if they share the same logic:"
            ]
          ]
        },
        "type": "text",
        "version": 1,
        "inline_content": [
          {
            "Text": "Cases can be combined in a comma-separated list if they share the same logic:"
          }
        ]
      },
      {
        "alive": true,
        "created_by": "bb760e2d-d679-4b64-b2a9-03005b21870a",
        "created_time": 1532156023177,
        "id": "e9b38632-de10-404f-9dfa-f385a99a0b19",
        "ignore_block_count": true,
        "last_edited_by": "bb760e2d-d679-4b64-b2a9-03005b21870a",
        "last_edited_time": 1532203248975,
        "parent_id": "77498e7b-3d31-464c-9def-3316dfe26415",
        "parent_table": "block",
        "properties": {
          "language": [
            [
              "Go"
            ]
          ],
          "title": [
            [
              "switch a + b {\ncase c, d:\n    // do something\ndefault:\n    // do something entirely different\n}"
            ]
          ]
        },
        "type": "code",
        "version": 3,
        "code": "switch a + b {\ncase c, d:\n    // do something\ndefault:\n    // do something entirely different\n}",
        "code_language": "Go"
      }
    ],
    "title": "switch statement",
    "format_page": {
      "page_cover": "",
      "page_cover_position": 0,
      "page_font": "",
      "page_full_width": true,
      "page_icon": "",
      "page_small_text": true
    }
  },
  "Users": [
    {
      "email": "kkowalczyk@gmail.com",
      "family_name": "Kowalczyk",
      "given_name": "Krzysztof",
      "id": "bb760e2d-d679-4b64-b2a9-03005b21870a",
      "locale": "en",
      "mobile_onboarding_completed": true,
      "onboarding_completed": true,
      "profile_photo": "https://s3-us-west-2.amazonaws.com/public.notion-static.com/2dcaa66c-7674-4ff6-9924-601785b63561/head-bw-640x960.png",
      "time_zone": "America/Los_Angeles",
      "version": 10
    }
  ],
  "Tables": null
}